.gitignore
MANIFEST.in
README.txt
bootstrap.py
plone.cfg
setup.cfg
setup.py
church/__init__.py
church.sermonaudio.egg-info/PKG-INFO
church.sermonaudio.egg-info/SOURCES.txt
church.sermonaudio.egg-info/dependency_links.txt
church.sermonaudio.egg-info/entry_points.txt
church.sermonaudio.egg-info/namespace_packages.txt
church.sermonaudio.egg-info/not-zip-safe
church.sermonaudio.egg-info/requires.txt
church.sermonaudio.egg-info/top_level.txt
church/sermonaudio/INTEGRATION.txt
church/sermonaudio/__init__.py
church/sermonaudio/configure.zcml
church/sermonaudio/tests.py
church/sermonaudio/upgrades.py
church/sermonaudio/upgrades.zcml
church/sermonaudio/browser/__init__.py
church/sermonaudio/browser/configure.zcml
church/sermonaudio/browser/sermons.py
church/sermonaudio/browser/static/download.png
church/sermonaudio/browser/static/play.png
church/sermonaudio/browser/static/script.js
church/sermonaudio/browser/static/sermon_icon.png
church/sermonaudio/browser/static/style.css
church/sermonaudio/browser/templates/sermons.pt
church/sermonaudio/locales/README.txt
church/sermonaudio/profiles/default/catalog.xml
church/sermonaudio/profiles/default/jsregistry.xml
church/sermonaudio/profiles/default/metadata.xml
church/sermonaudio/profiles/default/types.xml
church/sermonaudio/profiles/default/types/Folder.xml
church/sermonaudio/profiles/default/types/sermon.xml
church/sermonaudio/static/README.txt
docs/._HISTORY.txt
docs/HISTORY.txt
docs/INSTALL.txt
docs/LICENSE.txt