Metadata-Version: 1.1
Name: church.sermonaudio
Version: 1.0a9
Summary: Sermon Audio
Home-page: http://svn.plone.org/svn/collective/
Author: David Bain
Author-email: david@alteroo.com
License: GPL
Keywords: audio,archive,sermon
Platform: UNKNOWN
Classifier: Framework :: Plone
Classifier: Programming Language :: Python
Classifier: Topic :: Software Development :: Libraries :: Python Modules
